MANIFEST.in
setup.cfg
setup.py
tw2/__init__.py
tw2.tinymce.egg-info/PKG-INFO
tw2.tinymce.egg-info/SOURCES.txt
tw2.tinymce.egg-info/dependency_links.txt
tw2.tinymce.egg-info/entry_points.txt
tw2.tinymce.egg-info/namespace_packages.txt
tw2.tinymce.egg-info/not-zip-safe
tw2.tinymce.egg-info/requires.txt
tw2.tinymce.egg-info/top_level.txt
tw2/tinymce/__init__.py
tw2/tinymce/base.py
tw2/tinymce/samples.py
tw2/tinymce/widgets.py
tw2/tinymce/static/tinymce.css
tw2/tinymce/static/tinymce.js
tw2/tinymce/static/tiny_mce/license.txt
tw2/tinymce/static/tiny_mce/tiny_mce.js
tw2/tinymce/static/tiny_mce/tiny_mce_popup.js
tw2/tinymce/static/tiny_mce/tiny_mce_src.js
tw2/tinymce/static/tiny_mce/langs/en.js
tw2/tinymce/static/tiny_mce/plugins/advhr/editor_plugin.js
tw2/tinymce/static/tiny_mce/plugins/advhr/editor_plugin_src.js
tw2/tinymce/static/tiny_mce/plugins/advhr/rule.htm
tw2/tinymce/static/tiny_mce/plugins/advhr/css/advhr.css
tw2/tinymce/static/tiny_mce/plugins/advhr/js/rule.js
tw2/tinymce/static/tiny_mce/plugins/advhr/langs/en_dlg.js
tw2/tinymce/static/tiny_mce/plugins/advimage/editor_plugin.js
tw2/tinymce/static/tiny_mce/plugins/advimage/editor_plugin_src.js
tw2/tinymce/static/tiny_mce/plugins/advimage/image.htm
tw2/tinymce/static/tiny_mce/plugins/advimage/css/advimage.css
tw2/tinymce/static/tiny_mce/plugins/advimage/img/sample.gif
tw2/tinymce/static/tiny_mce/plugins/advimage/js/image.js
tw2/tinymce/static/tiny_mce/plugins/advimage/langs/en_dlg.js
tw2/tinymce/static/tiny_mce/plugins/advlink/editor_plugin.js
tw2/tinymce/static/tiny_mce/plugins/advlink/editor_plugin_src.js
tw2/tinymce/static/tiny_mce/plugins/advlink/link.htm
tw2/tinymce/static/tiny_mce/plugins/advlink/css/advlink.css
tw2/tinymce/static/tiny_mce/plugins/advlink/js/advlink.js
tw2/tinymce/static/tiny_mce/plugins/advlink/langs/en_dlg.js
tw2/tinymce/static/tiny_mce/plugins/advlist/editor_plugin.js
tw2/tinymce/static/tiny_mce/plugins/advlist/editor_plugin_src.js
tw2/tinymce/static/tiny_mce/plugins/autolink/editor_plugin.js
tw2/tinymce/static/tiny_mce/plugins/autolink/editor_plugin_src.js
tw2/tinymce/static/tiny_mce/plugins/autoresize/editor_plugin.js
tw2/tinymce/static/tiny_mce/plugins/autoresize/editor_plugin_src.js
tw2/tinymce/static/tiny_mce/plugins/autosave/editor_plugin.js
