Metadata-Version: 1.1
Name: tw2.tinymce
Version: 2.0.b4dev-20120523
Summary: TinyMCE for ToscaWidgets 2
Home-page: https://github.com/toscawidgets/tw2.tinymce
Author: Greg Jurman
Author-email: gdj2214@rit.edu
License: UNKNOWN
Keywords: toscawidgets.widgets
Platform: UNKNOWN
Classifier: Development Status :: 3 - Alpha
Classifier: Environment :: Web Environment
Classifier: Environment :: Web Environment :: ToscaWidgets
Classifier: Topic :: Software Development :: Libraries :: Python Modules
Classifier: Topic :: Software Development :: Widget Sets
Classifier: Intended Audience :: Developers
Classifier: Operating System :: OS Independent
Classifier: Programming Language :: Python
